{
  "schema_version": "1",
  "acceptance_id": "GATE-03",
  "run_id": "PF07-ACCEPTANCE-RUN",
  "started_at": "2026-07-19T16:17:58Z",
  "finished_at": "2026-07-19T16:18:21Z",
  "source_tree_sha256": "7adeeefeb919290998237c6b98f05332582eb18158d26ab1a81afef2b151c7ba",
  "command_or_probe": "recorded redaction of protected acceptance observation",
  "exit_code": 0,
  "observations": {
    "result": "PASS",
    "distinct_order_count": 3,
    "distinct_customer_alias_count": 3,
    "distinct_product_input_count": 3,
    "distinct_payload_hash_count": 3,
    "fixed_workflow_fixture_used": false
  },
  "artifact_hashes": {},
  "redaction_state": "PUBLIC_REDACTED",
  "redaction_transform": {
    "id": "pf07-public-evidence-redaction",
    "version": "1",
    "script_sha256": "3b0acb03398ab18e38428adda75db3f870fe52510093067c4fcd59061830cd46"
  },
  "source_acceptance_id": "GATE-03",
  "source_record_sha256": "e81b9cdf020e1d1d1cf10b9c10c6639e7cb87c0002bd3d2603b884b43ab8196e",
  "source_artifact_hashes": {
    "gate03_variable_input_trace": "b5ffcfcf87fcf4602b1198395290c41d85f5741094de3701896a682124065e72"
  }
}
