{
  "schema_version": "1",
  "acceptance_id": "GATE-08",
  "run_id": "PF07-REFINEMENT-ACCEPTANCE-RUN",
  "started_at": "2026-07-22T23:28:34Z",
  "finished_at": "2026-07-22T23:29:55Z",
  "source_tree_sha256": "06426537792092ecaebfd1214ce7f7008488dadbdbf6aea109057f6e5139d012",
  "command_or_probe": "recorded redaction of protected acceptance observation",
  "exit_code": 0,
  "observations": {
    "result": "PASS",
    "supported_event_types": 4,
    "missing_event_repairs": 4,
    "schedule_only_repairs": 1,
    "first_scan_inserted_rows": 4,
    "first_scan_scheduled_missing_rows": 4,
    "second_scan_mutations": 0,
    "payload_mutations": 0,
    "protected_cancellation_fact_used": true
  },
  "artifact_hashes": {},
  "redaction_state": "PUBLIC_REDACTED",
  "redaction_transform": {
    "id": "pf07-public-evidence-redaction",
    "version": "1",
    "script_sha256": "aaa1efd7f518423acdb6aad17d094427e473b48ecd424153e54ff959e7b5bae0"
  },
  "source_acceptance_id": "GATE-08",
  "source_record_sha256": "b6a97831269e4ab1b9bd325a98bcb88364bcfe2947b374d94cf9855992bd87ac",
  "source_artifact_hashes": {
    "gate08_reconciliation_trace": "a4d793af96d595653ece4c80400d75ca269b2afa6b4f71986a93245c1edeede1"
  }
}
