{
  "schema_version": "1",
  "acceptance_id": "GATE-10",
  "run_id": "PF07-REFINEMENT-ACCEPTANCE-RUN",
  "started_at": "2026-07-22T21:54:57Z",
  "finished_at": "2026-07-22T21:55:23Z",
  "source_tree_sha256": "f4c03b41e2e988396aa101356e2abd6c94e2e0a3fec4242a61873f719d7e25e5",
  "command_or_probe": "recorded redaction of protected acceptance observation",
  "exit_code": 0,
  "observations": {
    "result": "PASS",
    "https_mode": "ON_DEMAND_HTTPS_TUNNEL",
    "clean_compose_project": true,
    "fresh_wordpress_database_and_volume": true,
    "fresh_n8n_runtime_and_volume": true,
    "backup_artifact_count": 8,
    "original_quiescent_before_snapshot": true,
    "reprovisioned_workflow_credential_bindings": true,
    "restored_hubspot_credential_smoke": "PASS",
    "restored_slack_credential_smoke": "PASS",
    "new_order_created_and_paid": true,
    "restored_created_n8n_executions": 1,
    "restored_payment_n8n_executions": 1,
    "new_deal_count": 1,
    "payment_slack_posts": 1,
    "duplicate_additional_slack_posts": 0,
    "duplicate_n8n_executions": 0,
    "original_runtime_calls": 0,
    "active_runtime_after_restore": "RESTORED",
    "original_outbound_runtime_enabled": false,
    "restored_webhook_and_queue_enabled": true,
    "original_services_stopped": true,
    "formal_backup_manifest_verified": true
  },
  "artifact_hashes": {},
  "redaction_state": "PUBLIC_REDACTED",
  "redaction_transform": {
    "id": "pf07-public-evidence-redaction",
    "version": "1",
    "script_sha256": "aaa1efd7f518423acdb6aad17d094427e473b48ecd424153e54ff959e7b5bae0"
  },
  "source_acceptance_id": "GATE-10",
  "source_record_sha256": "e920c030274bf2bebb7a3dc0ee1abdf79c8dacf0eb370206f94b5af9b7320076",
  "source_artifact_hashes": {
    "gate10_restore_trace": "cda0e18863c68df0adaf90b73fdce3ddbf88b009c329d5d721cfc0a5a7db4d37"
  }
}
